{
  "entries": {
    "tap": {
      "homebrew/core": {
        "revision": "04c5a2074f6ead2a40de179c35627a720aa20620"
      },
      "homebrew/cask": {
        "revision": "7ab1aa1f30be3c4435a18e5db05f3e645b76183e"
      },
      "adoptopenjdk/openjdk": {
        "revision": "8b57564cc0fe84bffb0104078636df4ed34d0d8a"
      }
    },
    "brew": {
      "ack": {
        "version": "3.3.1",
        "bottle": false
      },
      "coreutils": {
        "version": "8.32",
        "bottle": {
          "cellar": "/usr/local/Cellar",
          "prefix": "/usr/local",
          "files": {
            "catalina": {
              "url": "https://homebrew.bintray.com/bottles/coreutils-8.32.catalina.bottle.tar.gz",
              "sha256": "67a4452d75a1882bd7fb977b384204edfa2758276d66290e595487922368e093"
            },
            "mojave": {
              "url": "https://homebrew.bintray.com/bottles/coreutils-8.32.mojave.bottle.tar.gz",
              "sha256": "5da6cb9dbc0a8144480dde2fb78eb0a5a1710490afc3697174f7e261ec69763f"
            },
            "high_sierra": {
              "url": "https://homebrew.bintray.com/bottles/coreutils-8.32.high_sierra.bottle.tar.gz",
              "sha256": "caa8cd8965727d0e805eccdc3e306cd0599720cdd0d5417cfcca03bead670663"
            }
          }
        }
      },
      "grc": {
        "version": "1.11.3_1",
        "bottle": false
      },
      "openssl": null,
      "node": {
        "version": "14.4.0",
        "bottle": {
          "cellar": ":any",
          "prefix": "/usr/local",
          "files": {
            "catalina": {
              "url": "https://homebrew.bintray.com/bottles/node-14.4.0.catalina.bottle.tar.gz",
              "sha256": "7fbf484b2c921451809192dba684a838ba387a4affc1d4380ebb607f95ccf0ec"
            },
            "mojave": {
              "url": "https://homebrew.bintray.com/bottles/node-14.4.0.mojave.bottle.tar.gz",
              "sha256": "06ef204701e93bbcf3909dba4ac9d3ca1d4df00a980f03cbeab390be1c562d34"
            },
            "high_sierra": {
              "url": "https://homebrew.bintray.com/bottles/node-14.4.0.high_sierra.bottle.tar.gz",
              "sha256": "68c7e5ff3e93bda3795d954b83609282f9ccf3cbe8096affeb28179d1fc1bd1d"
            }
          }
        }
      },
      "readline": {
        "version": "8.0.4",
        "bottle": {
          "cellar": ":any",
          "prefix": "/usr/local",
          "files": {
            "catalina": {
              "url": "https://homebrew.bintray.com/bottles/readline-8.0.4.catalina.bottle.tar.gz",
              "sha256": "6ae1c8e7c783f32bd22c6085caa4d838fed7fb386da7e40ca47b87ec9b1237d6"
            },
            "mojave": {
              "url": "https://homebrew.bintray.com/bottles/readline-8.0.4.mojave.bottle.tar.gz",
              "sha256": "29f7102a730ab39c8312cad1e7e439f6da2a67c452ce2b3380581eb185a5d8e8"
            },
            "high_sierra": {
              "url": "https://homebrew.bintray.com/bottles/readline-8.0.4.high_sierra.bottle.tar.gz",
              "sha256": "896a3d50ce8962ba56e853bdd590fadeabc00ab36475d143d6c2bea5cc15bb28"
            }
          }
        }
      },
      "postgresql": {
        "version": "12.3_4",
        "bottle": {
          "cellar": "/usr/local/Cellar",
          "prefix": "/usr/local",
          "files": {
            "catalina": {
              "url": "https://homebrew.bintray.com/bottles/postgresql-12.3_4.catalina.bottle.tar.gz",
              "sha256": "069912aa3d10ecb548eb2dddd7e3e1be61d1689d236b5993bce3e1a31811bcd0"
            },
            "mojave": {
              "url": "https://homebrew.bintray.com/bottles/postgresql-12.3_4.mojave.bottle.tar.gz",
              "sha256": "06eb65f3f17b6bf08344cbae35adc295f5c6da22420ee81d1e8fe2787e05a03b"
            },
            "high_sierra": {
              "url": "https://homebrew.bintray.com/bottles/postgresql-12.3_4.high_sierra.bottle.tar.gz",
              "sha256": "93e3b484a26931374ece4ee4f5abd4b3eac0a6e519d2fba696871f2342f0e513"
            }
          }
        }
      },
      "python3": null,
      "ruby": {
        "version": "2.7.1_2",
        "bottle": {
          "cellar": "/usr/local/Cellar",
          "prefix": "/usr/local",
          "files": {
            "catalina": {
              "url": "https://homebrew.bintray.com/bottles/ruby-2.7.1_2.catalina.bottle.tar.gz",
              "sha256": "c9ee36823a8dfe2686c6d7a3faf5061a032ed0b8e08d484f3ff2cda72d210a08"
            },
            "mojave": {
              "url": "https://homebrew.bintray.com/bottles/ruby-2.7.1_2.mojave.bottle.tar.gz",
              "sha256": "d597bee751f9419ea7b40d8125e4f58b2c1eb675b929fe85d8463a6e008b2250"
            },
            "high_sierra": {
              "url": "https://homebrew.bintray.com/bottles/ruby-2.7.1_2.high_sierra.bottle.tar.gz",
              "sha256": "345677b922e40e7324bbab0d68593a2bbef7aa3e8f636fd850295f3414758ed7"
            }
          }
        }
      },
      "ruby-build": {
        "version": "20200520",
        "bottle": false
      },
      "rbenv": {
        "version": "1.1.2",
        "bottle": {
          "cellar": ":any",
          "prefix": "/usr/local",
          "files": {
            "catalina": {
              "url": "https://homebrew.bintray.com/bottles/rbenv-1.1.2.catalina.bottle.tar.gz",
              "sha256": "503ed6d818502f00f031b9f49461934e252b9bfba2876e90a326fc27bb1052d6"
            },
            "mojave": {
              "url": "https://homebrew.bintray.com/bottles/rbenv-1.1.2.mojave.bottle.tar.gz",
              "sha256": "d1019098dee8d037587069398e5ad04e6d736f834dc44ae73943bec46b10b260"
            },
            "high_sierra": {
              "url": "https://homebrew.bintray.com/bottles/rbenv-1.1.2.high_sierra.bottle.tar.gz",
              "sha256": "b5984102794a9d39388ca1f6ec77965aeea29b971cc00cb5af8ede8ee6c926d6"
            },
            "sierra": {
              "url": "https://homebrew.bintray.com/bottles/rbenv-1.1.2.sierra.bottle.tar.gz",
              "sha256": "873175a851e5aa4f5b3438072030b945c252f08a9a07760c64dc045e2cce4724"
            }
          }
        }
      },
      "unrar": {
        "version": "5.9.3",
        "bottle": {
          "cellar": ":any",
          "prefix": "/usr/local",
          "files": {
            "catalina": {
              "url": "https://homebrew.bintray.com/bottles/unrar-5.9.3.catalina.bottle.tar.gz",
              "sha256": "7d9bc5d2dc49f1a007df7be45e6c2273dd9bedcfaa1f3c7ee04f9becfeb51974"
            },
            "mojave": {
              "url": "https://homebrew.bintray.com/bottles/unrar-5.9.3.mojave.bottle.tar.gz",
              "sha256": "4024ac60f589ac416b3ff229b468d2fff0c03dc6ecf88bafcdba03ffb2df39d4"
            },
            "high_sierra": {
              "url": "https://homebrew.bintray.com/bottles/unrar-5.9.3.high_sierra.bottle.tar.gz",
              "sha256": "8d16bf1854a72f4ae902426142bea57c3b3d98fa8a849c97fa4d926acfc101f3"
            }
          }
        }
      },
      "wget": {
        "version": "1.20.3_2",
        "bottle": {
          "cellar": "/usr/local/Cellar",
          "prefix": "/usr/local",
          "files": {
            "catalina": {
              "url": "https://homebrew.bintray.com/bottles/wget-1.20.3_2.catalina.bottle.tar.gz",
              "sha256": "ef65c759c5097a36323fa9c77756468649e8d1980a3a4e05695c05e39568967c"
            },
            "mojave": {
              "url": "https://homebrew.bintray.com/bottles/wget-1.20.3_2.mojave.bottle.tar.gz",
              "sha256": "28f4090610946a4eb207df102d841de23ced0d06ba31cb79e040d883906dcd4f"
            },
            "high_sierra": {
              "url": "https://homebrew.bintray.com/bottles/wget-1.20.3_2.high_sierra.bottle.tar.gz",
              "sha256": "91dd0caca9bd3f38c439d5a7b6f68440c4274945615fae035ff0a369264b8a2f"
            }
          }
        }
      },
      "zsh": {
        "version": "5.8",
        "bottle": {
          "cellar": "/usr/local/Cellar",
          "prefix": "/usr/local",
          "files": {
            "catalina": {
              "url": "https://homebrew.bintray.com/bottles/zsh-5.8.catalina.bottle.tar.gz",
              "sha256": "209d04a4d62f6162f1b6cf824d2c50b00b52cb812c04c1967e5b376573b5aef0"
            },
            "mojave": {
              "url": "https://homebrew.bintray.com/bottles/zsh-5.8.mojave.bottle.tar.gz",
              "sha256": "c5c35657637c97132efbaa0fd8e2add568aaa62adfe66e7d19f961f8e9506da9"
            },
            "high_sierra": {
              "url": "https://homebrew.bintray.com/bottles/zsh-5.8.high_sierra.bottle.tar.gz",
              "sha256": "029b8c6922f01bfd832dd0f4f940f99328d2495714c37c1dc7ef326d6fb1459e"
            }
          }
        }
      }
    },
    "cask": {
      "adoptopenjdk11": {
        "version": "11.0.7,10.1",
        "options": {
          "full_name": "adoptopenjdk11"
        }
      },
      "firefox": {
        "version": "77.0.1",
        "options": {
          "full_name": "firefox"
        }
      },
      "iterm2": {
        "version": "3.3.11",
        "options": {
          "full_name": "iterm2"
        }
      },
      "itsycal": {
        "version": "0.12.3",
        "options": {
          "full_name": "itsycal"
        }
      },
      "jetbrains-toolbox": {
        "version": "1.17.7018",
        "options": {
          "full_name": "jetbrains-toolbox"
        }
      },
      "licecap": {
        "version": "1.30",
        "options": {
          "full_name": "licecap"
        }
      },
      "postman": {
        "version": "7.26.1",
        "options": {
          "full_name": "postman"
        }
      },
      "sketch": {
        "version": "66.1-97080",
        "options": {
          "full_name": "sketch"
        }
      },
      "slack": {
        "version": "4.6.0",
        "options": {
          "full_name": "slack"
        }
      },
      "spotify": {
        "version": "latest",
        "options": {
          "full_name": "spotify"
        }
      },
      "visual-studio-code": {
        "version": "1.46.1",
        "options": {
          "full_name": "visual-studio-code"
        }
      },
      "vlc": {
        "version": "3.0.11",
        "options": {
          "full_name": "vlc"
        }
      }
    }
  },
  "system": {
    "macos": {
      "catalina": {
        "HOMEBREW_VERSION": "2.4.0",
        "HOMEBREW_PREFIX": "/usr/local",
        "Homebrew/homebrew-core": "04c5a2074f6ead2a40de179c35627a720aa20620",
        "CLT": "11.5.0.0.1.1588476445",
        "Xcode": "11.4.1",
        "macOS": "10.15.5"
      }
    }
  }
}
